calculadora_saraiva_lib/__init__.py
calculadora_saraiva_lib/operations.py
test_lib/__init__.py
test_lib/test_lib_main.py
calculadora_saraiva_lib-0.1.5.dist-info/METADATA
calculadora_saraiva_lib-0.1.5.dist-info/WHEEL
calculadora_saraiva_lib-0.1.5.dist-info/top_level.txt
calculadora_saraiva_lib-0.1.5.dist-info/RECORD
