Metadata-Version: 2.4
Name: calculadora_saraiva_lib
Version: 0.1.5
Summary: Biblioteca de operações matemáticas básicas em Python.
Home-page: https://github.com/saraivagustavo/calculadora-fastapi-lib-aula
Author: Gustavo Saraiva Mariano
Author-email: gsaraivam10@gmail.com
Classifier: Programming Language :: Python :: 3
Classifier: License :: OSI Approved :: MIT License
Classifier: Operating System :: OS Independent
Requires-Python: >=3.8
Dynamic: author
Dynamic: author-email
Dynamic: classifier
Dynamic: description
Dynamic: description-content-type
Dynamic: home-page
Dynamic: requires-python
Dynamic: summary
